tldr/__init__.py
tldr/github_adapter.py
tldr/signature_extractor_pygments.py
tldr/tldr_file_creator.py
tldr/llm_providers/__init__.py
tldr/llm_providers/claude_provider.py
tldr/llm_providers/grok_provider.py
tldr/llm_providers/llm_config.py
tldr/llm_providers/llm_factory.py
tldr/llm_providers/llm_provider.py
tldr_code-0.1.2.dist-info/licenses/LICENSE
tldr_code-0.1.2.dist-info/METADATA
tldr_code-0.1.2.dist-info/WHEEL
tldr_code-0.1.2.dist-info/entry_points.txt
tldr_code-0.1.2.dist-info/top_level.txt
tldr_code-0.1.2.dist-info/RECORD
