Metadata-Version: 2.4
Name: tldr-code
Version: 0.1.2
Summary: A Python tool that extracts function signatures from large codebases and generates concise summaries for LLM context preparation
Author-email: Chris Simoes <csimoes1@gmail.com>
Maintainer-email: Chris Simoes <csimoes1@gmail.com>
License: MIT
Project-URL: Homepage, https://github.com/csimoes1/tldr-code
Project-URL: Repository, https://github.com/csimoes1/tldr-code
Project-URL: Issues, https://github.com/csimoes1/tldr-code/issues
Project-URL: Documentation, https://github.com/csimoes1/tldr-code#readme
Keywords: code-analysis,function-signatures,llm,ai,code-documentation,pygments
Classifier: Development Status :: 4 - Beta
Classifier: Intended Audience :: Developers
Classifier: License :: OSI Approved :: MIT License
Classifier: Operating System :: OS Independent
Classifier: Programming Language :: Python :: 3
Classifier: Programming Language :: Python :: 3.8
Classifier: Programming Language :: Python :: 3.9
Classifier: Programming Language :: Python :: 3.10
Classifier: Programming Language :: Python :: 3.11
Classifier: Programming Language :: Python :: 3.12
Classifier: Topic :: Software Development :: Code Generators
Classifier: Topic :: Software Development :: Documentation
Classifier: Topic :: Text Processing :: Linguistic
Requires-Python: >=3.8
License-File: LICENSE
Requires-Dist: pygments-tldr>=2.19.1.3
Requires-Dist: requests>=2.25.0
Provides-Extra: ai
Requires-Dist: anthropic>=0.3.0; extra == "ai"
Requires-Dist: openai>=1.0.0; extra == "ai"
Provides-Extra: dev
Requires-Dist: pytest>=6.0; extra == "dev"
Requires-Dist: pytest-cov>=2.0; extra == "dev"
Requires-Dist: black>=21.0; extra == "dev"
Requires-Dist: flake8>=3.8; extra == "dev"
Requires-Dist: mypy>=0.900; extra == "dev"
Dynamic: license-file
